fstdb/__init__.py
fstdb/factory.py
fstdb/db/record.py
fstdb/db/tree_db.py
fstdb/db/context/__init__.py
fstdb/db/context/file_system_context.py
fstdb/db/context/record_context.py
fstdb/db/path_manager/__init__.py
fstdb/db/path_manager/name_checker.py
fstdb/db/path_manager/path_manager.py
fstdb/db/path_manager/tokenizer.py
fstdb/db/tools/viewer.py
fstdb/tools/file_finder.py
fstdb/tree/__init__.py
fstdb/tree/context.py
fstdb/tree/tree.py
fstdb-0.1.7.dist-info/licenses/LICENSE
fstdb-0.1.7.dist-info/METADATA
fstdb-0.1.7.dist-info/WHEEL
fstdb-0.1.7.dist-info/top_level.txt
fstdb-0.1.7.dist-info/RECORD
